Metadata-Version: 1.0
Name: intelligencer
Version: 0.1
Summary: Web and Data Automation Hub
Home-page: http://github.com/jgissend10/intelligencer
Author: James Szalay
Author-email: jamestszalay@gmail.com
License: MIT
Platform: UNKNOWN
